{
  "voice": {
    "timbre": "warm, weich, weiblich, sanft",
    "tone": "freundlich, ruhig, leicht lächelnd",
    "pace_wpm": 142,
    "pitch": "mittel-hell",
    "emphasis": "sanft",
    "pauses": "natürlich, kurze Atempausen"
  },
  "audio_settings": {
    "format": "wav",
    "sample_rate": 44100,
    "bitrate": "128k",
    "channels": 1
  },
  "meta": {
    "version": "1.0",
    "comment": "Dieses Profil beschreibt Mira’s Standardstimme. Es wird später automatisch mit dem Tages-Spruch kombiniert."
  }
}
